omint-0.1.1.dist-info/METADATA
omint-0.1.1.dist-info/WHEEL
omint/OMCConnection.py
omint/__init__.py
omint-0.1.1.dist-info/RECORD
