Metadata-Version: 2.1
Name: omint
Version: 0.1.1
Summary: Python interface to the OpenModelica compiler API.
Author-Email: Matthew Taylor <m.taylor@ncl-marine.com>
License: MIT
Requires-Python: >=3.12
Requires-Dist: zmq>=0.0.0
